simframe/__init__.py
simframe/frame/__init__.py
simframe/frame/abstractgroup.py
simframe/frame/field.py
simframe/frame/frame.py
simframe/frame/group.py
simframe/frame/heartbeat.py
simframe/frame/intvar.py
simframe/frame/updater.py
simframe/integration/__init__.py
simframe/integration/instruction.py
simframe/integration/integrator.py
simframe/integration/scheme.py
simframe/integration/schemes/__init__.py
simframe/integration/schemes/expl_1_euler.py
simframe/integration/schemes/expl_2_fehlberg_adptv.py
simframe/integration/schemes/expl_2_heun.py
simframe/integration/schemes/expl_2_heun_euler_adptv.py
simframe/integration/schemes/expl_2_midpoint.py
simframe/integration/schemes/expl_2_ralston.py
simframe/integration/schemes/expl_3_bogacki_shampine_adptv.py
simframe/integration/schemes/expl_3_gottlieb_shu_adptv.py
simframe/integration/schemes/expl_3_heun.py
simframe/integration/schemes/expl_3_kutta.py
simframe/integration/schemes/expl_3_ralston.py
simframe/integration/schemes/expl_3_ssprk.py
simframe/integration/schemes/expl_4_38rule.py
simframe/integration/schemes/expl_4_ralston.py
simframe/integration/schemes/expl_4_runge_kutta.py
simframe/integration/schemes/expl_5_cash_karp_adptv.py
simframe/integration/schemes/expl_5_dormand_prince_adptv.py
simframe/integration/schemes/impl_1_euler_direct.py
simframe/integration/schemes/impl_1_euler_gmres.py
simframe/integration/schemes/impl_2_midpoint_direct.py
simframe/integration/schemes/update.py
simframe/io/__init__.py
simframe/io/dump.py
simframe/io/progress.py
simframe/io/reader.py
simframe/io/writer.py
simframe/io/writers/__init__.py
simframe/io/writers/hdf5writer.py
simframe/io/writers/namespacewriter.py
simframe/utils/__init__.py
simframe/utils/color.py
simframe/utils/format.py
tests/__init__.py
tests/test_adaptive.py
tests/test_simple.py
simframe-1.0.4.dist-info/LICENSE
simframe-1.0.4.dist-info/METADATA
simframe-1.0.4.dist-info/WHEEL
simframe-1.0.4.dist-info/top_level.txt
simframe-1.0.4.dist-info/RECORD
