Metadata-Version: 2.1
Name: simframe
Version: 1.0.4
Summary: Framework for Scientific Simulations
Home-page: https://github.com/stammler/simframe
Author: Sebastian Stammler, Tilman Birnstiel
Author-email: sebastian.stammler@gmail.com, til.birnstiel@lmu.de
Maintainer: Sebastian Stammler
License: BSD
Project-URL: Source Code, https://github.com/stammler/simframe/
Project-URL: Documentation, https://simframe.readthedocs.io/
Keywords: numerical,simulation,integration,science,mathematics,physics
Classifier: Development Status :: 5 - Production/Stable
Classifier: Environment :: Console
Classifier: Intended Audience :: Developers
Classifier: Intended Audience :: Science/Research
Classifier: License :: OSI Approved :: BSD License
Classifier: Natural Language :: English
Classifier: Operating System :: OS Independent
Classifier: Programming Language :: Python
Classifier: Programming Language :: Python :: 3 :: Only
Classifier: Topic :: Education
Classifier: Topic :: Scientific/Engineering
Classifier: Topic :: Scientific/Engineering :: Mathematics
Classifier: Topic :: Scientific/Engineering :: Physics
License-File: LICENSE
Requires-Dist: dill
Requires-Dist: h5py
Requires-Dist: matplotlib
Requires-Dist: numpy
Requires-Dist: scipy
